chatbridge/__init__.py
chatbridge/chatbridge.py
chatbridge/cli.py
chatbridge-0.0.1.dist-info/AUTHORS.rst
chatbridge-0.0.1.dist-info/LICENSE
chatbridge-0.0.1.dist-info/METADATA
chatbridge-0.0.1.dist-info/WHEEL
chatbridge-0.0.1.dist-info/entry_points.txt
chatbridge-0.0.1.dist-info/top_level.txt
chatbridge-0.0.1.dist-info/RECORD
